oscillations/__init__.py
oscillations-1.1.1.dist-info/METADATA
oscillations-1.1.1.dist-info/WHEEL
oscillations-1.1.1.dist-info/top_level.txt
oscillations-1.1.1.dist-info/RECORD
